[{"id":"f6284d00.1a6078","type":"tab","label":"Dashboard","disabled":false,"info":""},{"id":"c4380994.00143","type":"tab","label":"IBM Cloud","disabled":false,"info":""},{"id":"4b27d013.4861d","type":"tab","label":"Azure Cloud","disabled":false,"info":""},{"id":"d8f5ad43.020828","type":"tab","label":"AWS","disabled":false,"info":""},{"id":"fb741332.a3e448","type":"tls-config","z":"","name":"","cert":"","key":"","ca":"","certname":"","keyname":"","caname":"","servername":"","verifyservercert":true},{"id":"77c7306.60f335","type":"ui_group","z":"","name":"Azure","tab":"b19a20b8.f0b908","order":5,"disp":true,"width":"6","collapse":true},{"id":"4c77493f.7f1f18","type":"ui_base","theme":{"name":"theme-light","lightTheme":{"default":"#0094CE","baseColor":"#0094CE","baseFont":"-apple-system,BlinkMacSystemFont,Segoe UI,Roboto,Oxygen-Sans,Ubuntu,Cantarell,Helvetica Neue,sans-serif","edited":true,"reset":false},"darkTheme":{"default":"#097479","baseColor":"#097479","baseFont":"-apple-system,BlinkMacSystemFont,Segoe UI,Roboto,Oxygen-Sans,Ubuntu,Cantarell,Helvetica Neue,sans-serif","edited":false},"customTheme":{"name":"Untitled Theme 1","default":"#4B7930","baseColor":"#4B7930","baseFont":"-apple-system,BlinkMacSystemFont,Segoe UI,Roboto,Oxygen-Sans,Ubuntu,Cantarell,Helvetica Neue,sans-serif"},"themeState":{"base-color":{"default":"#0094CE","value":"#0094CE","edited":false},"page-titlebar-backgroundColor":{"value":"#0094CE","edited":false},"page-backgroundColor":{"value":"#fafafa","edited":false},"page-sidebar-backgroundColor":{"value":"#ffffff","edited":false},"group-textColor":{"value":"#1bbfff","edited":false},"group-borderColor":{"value":"#ffffff","edited":false},"group-backgroundColor":{"value":"#ffffff","edited":false},"widget-textColor":{"value":"#111111","edited":false},"widget-backgroundColor":{"value":"#0094ce","edited":false},"widget-borderColor":{"value":"#ffffff","edited":false},"base-font":{"value":"-apple-system,BlinkMacSystemFont,Segoe UI,Roboto,Oxygen-Sans,Ubuntu,Cantarell,Helvetica Neue,sans-serif"}},"angularTheme":{"primary":"indigo","accents":"blue","warn":"red","background":"grey"}},"site":{"name":"Node-RED Dashboard","hideToolbar":"false","allowSwipe":"false","lockMenu":"false","allowTempTheme":"true","dateFormat":"DD/MM/YYYY","sizes":{"sx":48,"sy":48,"gx":6,"gy":6,"cx":6,"cy":6,"px":0,"py":0}}},{"id":"b19a20b8.f0b908","type":"ui_tab","z":"","name":"Find prime number","icon":"dashboard","order":1,"disabled":false,"hidden":false},{"id":"b2e4be11.2a4f6","type":"ui_group","z":"","name":"IBM Cloud","tab":"b19a20b8.f0b908","order":4,"disp":true,"width":"6","collapse":true},{"id":"562e22e8.d4b3a4","type":"ui_tab","z":"","name":"Is it prime","icon":"dashboard","disabled":false,"hidden":false},{"id":"547f6279.4ecb1c","type":"ui_group","z":"","name":"Find primes up to ","tab":"b19a20b8.f0b908","order":1,"disp":true,"width":"6","collapse":false},{"id":"3fb1456e.2c8252","type":"ui_group","z":"","name":"AWS","tab":"b19a20b8.f0b908","order":6,"disp":true,"width":"6","collapse":true},{"id":"6d9b0fd5.800908","type":"ui_group","z":"","name":"Is it prime","tab":"562e22e8.d4b3a4","disp":true,"width":"6","collapse":false},{"id":"ebbe323.36de5d","type":"ui_group","z":"","name":"Performance : Time in MS","tab":"b19a20b8.f0b908","order":2,"disp":true,"width":"6","collapse":false},{"id":"c883703e.e19ed","type":"ui_group","z":"","name":"History Chart","tab":"b19a20b8.f0b908","order":3,"disp":true,"width":"12","collapse":false},{"id":"2838d330.b34824","type":"ui_spacer","name":"spacer","group":"ebbe323.36de5d","order":7,"width":1,"height":1},{"id":"b90178f4.f1c88","type":"ui_group","z":"","name":"Delete History","tab":"b19a20b8.f0b908","order":7,"disp":true,"width":"6","collapse":true},{"id":"3964f3dd.1f5f94","type":"http request","z":"c4380994.00143","name":"Prime_List_JS","method":"GET","ret":"txt","paytoqs":true,"url":"https://aa0ccd31.eu-de.apigw.appdomain.cloud/prime/ListJS","tls":"","persist":false,"proxy":"","authType":"","x":420,"y":180,"wires":[["5f373023.95c608","54621e7c.037688"]]},{"id":"14fc53c8.bbfad4","type":"http request","z":"c4380994.00143","name":"Is_Prime_JS","method":"GET","ret":"txt","paytoqs":true,"url":"https://aa0ccd31.eu-de.apigw.appdomain.cloud/prime/IsJS","tls":"","persist":false,"proxy":"","authType":"","x":390,"y":540,"wires":[[]]},{"id":"93e6e629.bc8608","type":"inject","z":"c4380994.00143","name":"number","topic":"","payload":"{\"number\":7}","payloadType":"json","repeat":"","crontab":"","once":false,"onceDelay":0.1,"x":130,"y":540,"wires":[["14fc53c8.bbfad4"]]},{"id":"1b364b00.ed73bd","type":"http request","z":"c4380994.00143","name":"Prime_List_Java","method":"GET","ret":"txt","paytoqs":true,"url":"https://aa0ccd31.eu-de.apigw.appdomain.cloud/prime/ListJava","tls":"","persist":false,"proxy":"","authType":"","x":400,"y":340,"wires":[["21a2769c.df1332","77b28639.8dd52"]]},{"id":"ee3896e7.d2e81","type":"http request","z":"c4380994.00143","name":"Is_Prime_Java","method":"GET","ret":"txt","paytoqs":true,"url":"https://aa0ccd31.eu-de.apigw.appdomain.cloud/prime/IsJava","tls":"","persist":false,"proxy":"","authType":"","x":380,"y":600,"wires":[[]]},{"id":"536a8cae.d775cc","type":"inject","z":"c4380994.00143","name":"number","topic":"","payload":"{\"number\":7}","payloadType":"json","repeat":"","crontab":"","once":false,"onceDelay":0.1,"x":130,"y":600,"wires":[["ee3896e7.d2e81"]]},{"id":"31f6f17d.da2936","type":"http request","z":"4b27d013.4861d","name":"Prime_List_JS","method":"GET","ret":"txt","paytoqs":true,"url":"https://cloud-compare.azurewebsites.net/api/PrimeList?code=eHgE/VcGx4Dr2FvOfqh1HwnMmopiXSsbg83gQrdsgiDaUiz7fVCUTw==","tls":"","persist":false,"proxy":"","authType":"","x":380,"y":200,"wires":[["d05012be.957bb8","b82920fb.cd2ae8"]]},{"id":"f8646b57.f5aae","type":"debug","z":"4b27d013.4861d","name":"","active":true,"tosidebar":true,"console":false,"tostatus":false,"complete":"false","x":690,"y":520,"wires":[]},{"id":"56f8875.8a18978","type":"http request","z":"4b27d013.4861d","name":"Is_Prime_JS","method":"GET","ret":"txt","paytoqs":true,"url":"https://cloud-compare.azurewebsites.net/api/IsPrime?code=LT8yKAr/U0AvAF59CaiFIjQ5Cc1Qif5gH9DXuUp7FZ0H3JjF6nsqEA==","tls":"","persist":false,"proxy":"","authType":"","x":450,"y":480,"wires":[["f8646b57.f5aae"]]},{"id":"427e09c5.44db08","type":"inject","z":"4b27d013.4861d","name":"number","topic":"","payload":"{\"number\":7}","payloadType":"json","repeat":"","crontab":"","once":false,"onceDelay":0.1,"x":190,"y":480,"wires":[["56f8875.8a18978"]]},{"id":"c579385c.7002a8","type":"inject","z":"4b27d013.4861d","name":"max - name","topic":"","payload":"{\"name\":20}","payloadType":"json","repeat":"","crontab":"","once":false,"onceDelay":0.1,"x":130,"y":560,"wires":[[]]},{"id":"e1e6b0a5.924ac8","type":"http request","z":"4b27d013.4861d","name":"Prime_List_Java","method":"GET","ret":"txt","paytoqs":true,"url":"https://primelistjava.azurewebsites.net/api/PrimeListJava?code=py/iehV9wFu86NX0sapsg9VJXT3RlMt7pHpv1ACLu3qS6EwX3SBRJQ==","tls":"","persist":false,"proxy":"","authType":"","x":360,"y":360,"wires":[["9eb8cb97.1337d8","2bf1e61a.9fd1ea"]]},{"id":"97b2b67.69354c8","type":"http request","z":"4b27d013.4861d","name":"Is_Prime_Java","method":"GET","ret":"txt","paytoqs":true,"url":"https://cloud-java.azurewebsites.net/api/IsPrimeJava?code=6qwwMfBIIypTBX1xpe2I2j6acR4p9oUkDCfcFyRr69NkUREc8g4PJA==","tls":"","persist":false,"proxy":"","authType":"","x":440,"y":640,"wires":[["f8646b57.f5aae"]]},{"id":"7ccedce5.7811b4","type":"inject","z":"4b27d013.4861d","name":"number - name","topic":"","payload":"{\"name\":8}","payloadType":"json","repeat":"","crontab":"","once":false,"onceDelay":0.1,"x":220,"y":640,"wires":[["97b2b67.69354c8"]]},{"id":"7f44f6d3.23394","type":"http request","z":"d8f5ad43.020828","name":"Prime_List_JS","method":"GET","ret":"txt","paytoqs":true,"url":"https://mt4qfaokvf.execute-api.us-east-2.amazonaws.com/prod/primelistjs","tls":"","persist":false,"proxy":"","authType":"","x":420,"y":120,"wires":[["18d77805.1b543","69fbd934.1bc1e8"]]},{"id":"a4277f42.59c738","type":"http request","z":"d8f5ad43.020828","name":"Is_Prime_JS","method":"GET","ret":"txt","paytoqs":true,"url":"https://mt4qfaokvf.execute-api.us-east-2.amazonaws.com/prod/isprimejs","tls":"","persist":false,"proxy":"","authType":"","x":450,"y":520,"wires":[[]]},{"id":"e056d058.4f2fd8","type":"inject","z":"d8f5ad43.020828","name":"number","topic":"","payload":"{\"number\":70}","payloadType":"json","repeat":"","crontab":"","once":false,"onceDelay":0.1,"x":190,"y":520,"wires":[["a4277f42.59c738"]]},{"id":"e9ae427b.328a68","type":"http request","z":"d8f5ad43.020828","name":"Prime_List_Java","method":"GET","ret":"txt","paytoqs":true,"url":"https://mt4qfaokvf.execute-api.us-east-2.amazonaws.com/prod/primelistjava","tls":"","persist":false,"proxy":"","authType":"","x":400,"y":280,"wires":[["d273b86b.75ea2","3c16fb97.0d1db4"]]},{"id":"2ee5b1b1.dc87f6","type":"http request","z":"d8f5ad43.020828","name":"Is_Prime_Java","method":"GET","ret":"txt","paytoqs":true,"url":"https://mt4qfaokvf.execute-api.us-east-2.amazonaws.com/prod/isprimejava","tls":"","persist":false,"proxy":"","authType":"","x":440,"y":600,"wires":[[]]},{"id":"43f833f0.cbf8e4","type":"inject","z":"d8f5ad43.020828","name":"number - name","topic":"","payload":"{\"number\":7}","payloadType":"json","repeat":"","crontab":"","once":false,"onceDelay":0.1,"x":220,"y":600,"wires":[["2ee5b1b1.dc87f6"]]},{"id":"dcb5f920.ef7d5","type":"ui_text_input","z":"f6284d00.1a6078","name":"","label":"Max number","tooltip":"the function will calculate all prime number up to this max number","group":"547f6279.4ecb1c","order":1,"width":0,"height":0,"passthru":false,"mode":"number","delay":300,"topic":"","x":170,"y":360,"wires":[["dda0ace9.0d27f8"]]},{"id":"f9d4c5e4.add17","type":"ui_button","z":"f6284d00.1a6078","name":"","group":"547f6279.4ecb1c","order":2,"width":0,"height":0,"passthru":false,"label":"button","tooltip":"","color":"","bgcolor":"","icon":"play_circle_outline","payload":"[]","payloadType":"json","topic":"","x":210,"y":200,"wires":[["9cb3444e.e3994","11fee3e1.94e62c"]]},{"id":"dda0ace9.0d27f8","type":"function","z":"f6284d00.1a6078","name":"save number","func":"var max = msg.payload;\nglobal.set('max',max);\nreturn msg;","outputs":1,"noerr":0,"x":300,"y":440,"wires":[[]]},{"id":"9cb3444e.e3994","type":"function","z":"f6284d00.1a6078","name":"Mashup","func":"var max=global.get('max') || 0;\nmsg.payload = {\"max\":max};\nvar n = {\"name\":max};\nvar m = {\"payload\":n}\n\nreturn [msg,m,{\"payload\":\"\"},null ];","outputs":6,"noerr":0,"x":380,"y":200,"wires":[["9452761f.e2b408"],["1c21dd24.56d93b"],["f1d21453.0db0a8"],[],[],[]]},{"id":"c83d144d.6944e","type":"inject","z":"f6284d00.1a6078","name":"","topic":"","payload":"","payloadType":"date","repeat":"","crontab":"","once":false,"onceDelay":0.1,"x":160,"y":120,"wires":[["9cb3444e.e3994"]]},{"id":"53e261e6.bb3858","type":"debug","z":"c4380994.00143","name":"","active":true,"tosidebar":true,"console":false,"tostatus":false,"complete":"true","targetType":"full","x":610,"y":480,"wires":[]},{"id":"9452761f.e2b408","type":"link out","z":"f6284d00.1a6078","name":"IBM/AWS","links":["7feb03e.661e7fc","4e42bd78.bad154","81334913.c57d38","3c60cafd.14714e","e3e91ca1.00f8b8","a05648f4.cf765"],"x":475,"y":100,"wires":[]},{"id":"7feb03e.661e7fc","type":"link in","z":"c4380994.00143","name":"","links":["9452761f.e2b408","5fdf9d6b.9f3cdc"],"x":215,"y":180,"wires":[["3964f3dd.1f5f94","54621e7c.037688"]]},{"id":"54621e7c.037688","type":"interval-length","z":"c4380994.00143","format":"mills","bytopic":true,"minimum":"","maximum":"","window":"","timeout":false,"msgTimeout":"","minimumunit":"msecs","maximumunit":"msecs","windowunit":"msecs","msgTimeoutUnit":"secs","reset":false,"startup":false,"msgField":"payload","timestampField":"timestamp","repeatTimeout":false,"name":"","x":440,"y":120,"wires":[["6911cf49.2552b8","763b3081.7a185"],[]]},{"id":"5f373023.95c608","type":"ui_text","z":"c4380994.00143","group":"b2e4be11.2a4f6","order":2,"width":"6","height":"3","name":"","label":"IBM Cloud - Prime List - Javascript","format":"{{msg.payload}}","layout":"col-center","x":740,"y":180,"wires":[]},{"id":"21a2769c.df1332","type":"ui_text","z":"c4380994.00143","group":"b2e4be11.2a4f6","order":2,"width":"6","height":"3","name":"","label":"IBM Cloud - Prime List - Java","format":"{{msg.payload}}","layout":"col-center","x":730,"y":340,"wires":[]},{"id":"7c2cb46a.6a7afc","type":"ui_text_input","z":"f6284d00.1a6078","name":"","label":"Is Prime","tooltip":"the function will calculate all prime number up to this max number","group":"6d9b0fd5.800908","order":1,"width":0,"height":0,"passthru":false,"mode":"number","delay":300,"topic":"","x":160,"y":520,"wires":[["8556908a.581fb"]]},{"id":"8556908a.581fb","type":"function","z":"f6284d00.1a6078","name":"save number","func":"var number = msg.payload;\nglobal.set('number',number);\nreturn msg;","outputs":1,"noerr":0,"x":300,"y":600,"wires":[[]]},{"id":"883a1e8.18d6fe","type":"ui_button","z":"f6284d00.1a6078","name":"","group":"6d9b0fd5.800908","order":2,"width":0,"height":0,"passthru":false,"label":"Is it prime","tooltip":"","color":"","bgcolor":"","icon":"play_circle_outline","payload":"","payloadType":"str","topic":"","x":260,"y":800,"wires":[["c5a121a6.35fb1"]]},{"id":"c5a121a6.35fb1","type":"function","z":"f6284d00.1a6078","name":"Mashup","func":"var number=global.get('number') || 0;\nmsg.payload = {\"number\":number};\nvar n = {\"name\":number};\nvar m = {\"payload\":n}\n\nreturn [msg,m,{\"payload\":\"\"},null ];","outputs":6,"noerr":0,"x":420,"y":800,"wires":[["974cc2ae.e9a21"],[],[],[],[],[]]},{"id":"974cc2ae.e9a21","type":"debug","z":"f6284d00.1a6078","name":"","active":true,"tosidebar":true,"console":false,"tostatus":false,"complete":"true","targetType":"full","x":650,"y":760,"wires":[]},{"id":"81334913.c57d38","type":"link in","z":"d8f5ad43.020828","name":"","links":["9452761f.e2b408","5fdf9d6b.9f3cdc"],"x":155,"y":120,"wires":[["7f44f6d3.23394","69fbd934.1bc1e8"]]},{"id":"3c60cafd.14714e","type":"link in","z":"d8f5ad43.020828","name":"","links":["9452761f.e2b408","5fdf9d6b.9f3cdc"],"x":155,"y":280,"wires":[["e9ae427b.328a68","d273b86b.75ea2"]]},{"id":"e3e91ca1.00f8b8","type":"link in","z":"c4380994.00143","name":"","links":["9452761f.e2b408","5fdf9d6b.9f3cdc"],"x":215,"y":340,"wires":[["1b364b00.ed73bd","77b28639.8dd52"]]},{"id":"18d77805.1b543","type":"ui_text","z":"d8f5ad43.020828","group":"3fb1456e.2c8252","order":0,"width":"6","height":"3","name":"","label":"AWS - Prime List - Javascript","format":"{{msg.payload}}","layout":"col-center","x":710,"y":120,"wires":[]},{"id":"3c16fb97.0d1db4","type":"ui_text","z":"d8f5ad43.020828","group":"3fb1456e.2c8252","order":0,"width":"6","height":"3","name":"","label":"AWS - Prime List - Java","format":"{{msg.payload}}","layout":"col-center","x":690,"y":280,"wires":[]},{"id":"9eb8cb97.1337d8","type":"ui_text","z":"4b27d013.4861d","group":"77c7306.60f335","order":2,"width":"6","height":"3","name":"","label":"Azure - Prime List - Java","format":"{{msg.payload}}","layout":"col-center","x":650,"y":360,"wires":[]},{"id":"d05012be.957bb8","type":"ui_text","z":"4b27d013.4861d","group":"77c7306.60f335","order":2,"width":"6","height":"3","name":"","label":"Azure - Prime List - Javascript","format":"{{msg.payload}}","layout":"col-center","x":670,"y":200,"wires":[]},{"id":"a05648f4.cf765","type":"link in","z":"4b27d013.4861d","name":"","links":["9452761f.e2b408","5fdf9d6b.9f3cdc"],"x":155,"y":200,"wires":[["31f6f17d.da2936","b82920fb.cd2ae8"]]},{"id":"6911cf49.2552b8","type":"ui_text","z":"c4380994.00143","group":"ebbe323.36de5d","order":1,"width":0,"height":0,"name":"","label":"IBM Cloud Javascript","format":"{{msg.payload}}","layout":"row-spread","x":680,"y":100,"wires":[]},{"id":"77b28639.8dd52","type":"interval-length","z":"c4380994.00143","format":"mills","bytopic":false,"minimum":"","maximum":"","window":"","timeout":false,"msgTimeout":"10","minimumunit":"msecs","maximumunit":"msecs","windowunit":"msecs","msgTimeoutUnit":"secs","reset":false,"startup":false,"msgField":"payload","timestampField":"timestamp","repeatTimeout":false,"name":"","x":400,"y":300,"wires":[["f3da699.c2cad98","a9fa698b.14d1c","53e261e6.bb3858"],[]]},{"id":"f3da699.c2cad98","type":"ui_text","z":"c4380994.00143","group":"ebbe323.36de5d","order":2,"width":0,"height":0,"name":"","label":"IBM Cloud Java","format":"{{msg.payload}}","layout":"row-spread","x":660,"y":280,"wires":[]},{"id":"f1d21453.0db0a8","type":"link out","z":"f6284d00.1a6078","name":"Init","links":["5f44a22.fdba0dc","c9d0c66e.44b3f","e2f8b971.a7b29","671e522e.d47fbc","bc74415a.eaf068","d38c3b2e.1dede"],"x":560,"y":240,"wires":[]},{"id":"5f44a22.fdba0dc","type":"link in","z":"c4380994.00143","name":"","links":["f1d21453.0db0a8"],"x":440,"y":60,"wires":[["6911cf49.2552b8"]]},{"id":"c9d0c66e.44b3f","type":"link in","z":"c4380994.00143","name":"","links":["f1d21453.0db0a8"],"x":495,"y":260,"wires":[["f3da699.c2cad98"]]},{"id":"e2f8b971.a7b29","type":"link in","z":"4b27d013.4861d","name":"","links":["f1d21453.0db0a8"],"x":335,"y":60,"wires":[["f2277590.b22eb"]]},{"id":"b82920fb.cd2ae8","type":"interval-length","z":"4b27d013.4861d","format":"mills","bytopic":false,"minimum":"","maximum":"","window":"","timeout":false,"msgTimeout":"10","minimumunit":"msecs","maximumunit":"msecs","windowunit":"msecs","msgTimeoutUnit":"secs","reset":false,"startup":false,"msgField":"payload","timestampField":"timestamp","repeatTimeout":false,"name":"","x":380,"y":160,"wires":[["f2277590.b22eb","d891f36c.8043d"],[]]},{"id":"f2277590.b22eb","type":"ui_text","z":"4b27d013.4861d","group":"ebbe323.36de5d","order":5,"width":0,"height":0,"name":"","label":"Azure Javascript","format":"{{msg.payload}}","layout":"row-spread","x":630,"y":140,"wires":[]},{"id":"895d8a07.8bca58","type":"ui_text","z":"4b27d013.4861d","group":"ebbe323.36de5d","order":6,"width":0,"height":0,"name":"","label":"Azure Java","format":"{{msg.payload}}","layout":"row-spread","x":610,"y":300,"wires":[]},{"id":"671e522e.d47fbc","type":"link in","z":"4b27d013.4861d","name":"","links":["f1d21453.0db0a8"],"x":355,"y":260,"wires":[["895d8a07.8bca58"]]},{"id":"bc74415a.eaf068","type":"link in","z":"d8f5ad43.020828","name":"","links":["f1d21453.0db0a8"],"x":495,"y":20,"wires":[["b653da1.d3f98a8"]]},{"id":"b653da1.d3f98a8","type":"ui_text","z":"d8f5ad43.020828","group":"ebbe323.36de5d","order":3,"width":0,"height":0,"name":"","label":"AWS Javascript","format":"{{msg.payload}}","layout":"row-spread","x":680,"y":60,"wires":[]},{"id":"d38c3b2e.1dede","type":"link in","z":"d8f5ad43.020828","name":"","links":["f1d21453.0db0a8"],"x":475,"y":180,"wires":[["f5ea324b.557da"]]},{"id":"f5ea324b.557da","type":"ui_text","z":"d8f5ad43.020828","group":"ebbe323.36de5d","order":4,"width":0,"height":0,"name":"","label":"AWS Java","format":"{{msg.payload}}","layout":"row-spread","x":650,"y":220,"wires":[]},{"id":"69fbd934.1bc1e8","type":"interval-length","z":"d8f5ad43.020828","format":"mills","bytopic":false,"minimum":"","maximum":"","window":"","timeout":false,"msgTimeout":"10","minimumunit":"msecs","maximumunit":"msecs","windowunit":"msecs","msgTimeoutUnit":"secs","reset":false,"startup":false,"msgField":"payload","timestampField":"timestamp","repeatTimeout":false,"name":"","x":420,"y":80,"wires":[["b653da1.d3f98a8","7a9a18a.21d5be8"],[]]},{"id":"d273b86b.75ea2","type":"interval-length","z":"d8f5ad43.020828","format":"mills","bytopic":false,"minimum":"","maximum":"","window":"","timeout":false,"msgTimeout":"10","minimumunit":"msecs","maximumunit":"msecs","windowunit":"msecs","msgTimeoutUnit":"msecs","reset":false,"startup":false,"msgField":"payload","timestampField":"timestamp","repeatTimeout":false,"name":"","x":400,"y":220,"wires":[["f5ea324b.557da","baa686c8.d3215"],[]]},{"id":"2bf1e61a.9fd1ea","type":"interval-length","z":"4b27d013.4861d","format":"mills","bytopic":false,"minimum":"","maximum":"","window":"","timeout":false,"msgTimeout":"10","minimumunit":"msecs","maximumunit":"msecs","windowunit":"msecs","msgTimeoutUnit":"msecs","reset":false,"startup":false,"msgField":"payload","timestampField":"timestamp","repeatTimeout":false,"name":"","x":320,"y":320,"wires":[["895d8a07.8bca58","25d7997f.cde226"],[]]},{"id":"1c21dd24.56d93b","type":"link out","z":"f6284d00.1a6078","name":"name","links":["f1c35e86.5b75f8"],"x":560,"y":200,"wires":[]},{"id":"f1c35e86.5b75f8","type":"link in","z":"4b27d013.4861d","name":"","links":["1c21dd24.56d93b"],"x":120,"y":360,"wires":[["e1e6b0a5.924ac8","2bf1e61a.9fd1ea"]]},{"id":"f5973c7c.8fd7e8","type":"link in","z":"f6284d00.1a6078","name":"Chart","links":["ebe3be.a451bc4","6e72dbf.509e124","80ff7582.623ac"],"x":675,"y":320,"wires":[["5ebf0925.282c48"]]},{"id":"763b3081.7a185","type":"change","z":"c4380994.00143","name":"JS","rules":[{"t":"set","p":"topic","pt":"msg","to":"IBM Cloud Javascript","tot":"str"}],"action":"","property":"","from":"","to":"","reg":false,"x":1090,"y":160,"wires":[["ebe3be.a451bc4"]]},{"id":"ebe3be.a451bc4","type":"link out","z":"c4380994.00143","name":"","links":["f5973c7c.8fd7e8"],"x":1220,"y":220,"wires":[]},{"id":"a9fa698b.14d1c","type":"change","z":"c4380994.00143","name":"Java","rules":[{"t":"set","p":"topic","pt":"msg","to":"IBM Cloud Java","tot":"str"}],"action":"","property":"","from":"","to":"","reg":false,"x":1110,"y":280,"wires":[["ebe3be.a451bc4"]]},{"id":"d891f36c.8043d","type":"change","z":"4b27d013.4861d","name":"JS","rules":[{"t":"set","p":"topic","pt":"msg","to":"Azure Javascript","tot":"str"}],"action":"","property":"","from":"","to":"","reg":false,"x":950,"y":220,"wires":[["6e72dbf.509e124"]]},{"id":"25d7997f.cde226","type":"change","z":"4b27d013.4861d","name":"Java","rules":[{"t":"set","p":"topic","pt":"msg","to":"Azure Java","tot":"str"}],"action":"","property":"","from":"","to":"","reg":false,"x":970,"y":340,"wires":[["6e72dbf.509e124"]]},{"id":"6e72dbf.509e124","type":"link out","z":"4b27d013.4861d","name":"","links":["f5973c7c.8fd7e8"],"x":1080,"y":280,"wires":[]},{"id":"7a9a18a.21d5be8","type":"change","z":"d8f5ad43.020828","name":"JS","rules":[{"t":"set","p":"topic","pt":"msg","to":"AWS Javascript","tot":"str"}],"action":"","property":"","from":"","to":"","reg":false,"x":990,"y":140,"wires":[["80ff7582.623ac"]]},{"id":"baa686c8.d3215","type":"change","z":"d8f5ad43.020828","name":"Java","rules":[{"t":"set","p":"topic","pt":"msg","to":"AWS Java","tot":"str"}],"action":"","property":"","from":"","to":"","reg":false,"x":1010,"y":260,"wires":[["80ff7582.623ac"]]},{"id":"80ff7582.623ac","type":"link out","z":"d8f5ad43.020828","name":"","links":["f5973c7c.8fd7e8"],"x":1120,"y":200,"wires":[]},{"id":"11fee3e1.94e62c","type":"ui_chart","z":"f6284d00.1a6078","name":"","group":"ebbe323.36de5d","order":8,"width":0,"height":0,"label":"Fastest to slowest","chartType":"pie","legend":"true","xformat":"HH:mm","interpolate":"linear","nodata":"","dot":false,"ymin":"","ymax":"","removeOlder":1,"removeOlderPoints":"1000","removeOlderUnit":"604800","cutout":0,"useOneColor":false,"colors":["#1f77b4","#aec7e8","#ff7f0e","#2ca02c","#98df8a","#d62728","#ff9896","#9467bd","#c5b0d5"],"useOldStyle":false,"outputs":1,"x":940,"y":280,"wires":[[]]},{"id":"bc8a1951.70d498","type":"ui_chart","z":"f6284d00.1a6078","name":"","group":"c883703e.e19ed","order":7,"width":0,"height":0,"label":"chart","chartType":"line","legend":"true","xformat":"HH:mm","interpolate":"linear","nodata":"","dot":true,"ymin":"","ymax":"","removeOlder":1,"removeOlderPoints":"500","removeOlderUnit":"604800","cutout":0,"useOneColor":false,"colors":["#1f77b4","#aec7e8","#ff7f0e","#2ca02c","#98df8a","#d62728","#ff9896","#9467bd","#c5b0d5"],"useOldStyle":false,"outputs":1,"x":1050,"y":340,"wires":[[]]},{"id":"5ebf0925.282c48","type":"function","z":"f6284d00.1a6078","name":"","func":"\n\nif (msg.statusCode == 200)\nreturn [msg,null]\nelse \nreturn[null,msg] ","outputs":2,"noerr":0,"x":780,"y":340,"wires":[["bc8a1951.70d498","11fee3e1.94e62c"],[]]},{"id":"39ee5837.b6bfe8","type":"switch","z":"c4380994.00143","name":"","property":"payload","propertyType":"msg","rules":[{"t":"eq","v":"","vt":"str"}],"checkall":"true","repair":false,"outputs":1,"x":880,"y":460,"wires":[[]]},{"id":"f4680bd3.419a5","type":"inject","z":"f6284d00.1a6078","name":"","topic":"","payload":"[]","payloadType":"json","repeat":"","crontab":"","once":false,"onceDelay":0.1,"x":790,"y":140,"wires":[[]]},{"id":"bfde0a76.5e138","type":"ui_button","z":"f6284d00.1a6078","name":"","group":"b90178f4.f1c88","order":0,"width":0,"height":0,"passthru":false,"label":"Delete History","tooltip":"","color":"black","bgcolor":"red","icon":"delete","payload":"[]","payloadType":"json","topic":"","x":840,"y":420,"wires":[["bc8a1951.70d498","11fee3e1.94e62c"]]}]